blipscore_config/__init__.py
blipscore_config/config.py
take_blipscore/__init__.py
take_blipscore/run.py
take_blipscore/data_validation/__init__.py
take_blipscore/data_validation/main.py
take_blipscore/data_validation/run_input_validation.py
take_blipscore/processing/__init__.py
take_blipscore/processing/metrics.py
take_blipscore-1.0.0.dist-info/LICENSE
take_blipscore-1.0.0.dist-info/METADATA
take_blipscore-1.0.0.dist-info/WHEEL
take_blipscore-1.0.0.dist-info/top_level.txt
take_blipscore-1.0.0.dist-info/RECORD
