Metadata-Version: 2.1
Name: take-blipscore
Version: 1.0.0
Summary: Generate Blip Score metric.
Home-page: UNKNOWN
Author: squad XD
Author-email: anaytics.ped@take.net
Maintainer: Take - D&A
Maintainer-email: anaytics.ped@take.net
License: MIT License
Keywords: BLiP,score,metrics
Platform: UNKNOWN
Classifier: Programming Language :: Python :: 3.7
Classifier: Operating System :: OS Independent
Requires-Python: >=3.7
Requires-Dist: numpy (==1.19.4)
